expensemanager/__init__.py
expensemanager/expensemanager.py
expensemanager-1.5.dist-info/METADATA
expensemanager-1.5.dist-info/WHEEL
expensemanager-1.5.dist-info/top_level.txt
expensemanager-1.5.dist-info/RECORD
