Metadata-Version: 2.1
Name: expensemanager
Version: 1.5
Summary: generate balance summary and manage expenses 
Author-email: "PavanKumarReddy.U" <pav1reddie@gmail.com>
Requires-Python: >=3.7
